dwim/__init__.py
dwim/cli.py
dwim/exceptions.py
dwim-0.3.1.dist-info/DESCRIPTION.rst
dwim-0.3.1.dist-info/METADATA
dwim-0.3.1.dist-info/RECORD
dwim-0.3.1.dist-info/WHEEL
dwim-0.3.1.dist-info/entry_points.txt
dwim-0.3.1.dist-info/metadata.json
dwim-0.3.1.dist-info/top_level.txt
