Metadata-Version: 2.0
Name: dwim
Version: 0.3.1
Summary: Location aware application launcher
Home-page: https://dwim.readthedocs.io/en/latest/
Author: Peter Odding
Author-email: peter@peterodding.com
License: UNKNOWN
Platform: UNKNOWN
Classifier: Development Status :: 5 - Production/Stable
Classifier: Environment :: Console
Classifier: Intended Audience :: Developers
Classifier: Intended Audience :: End Users/Desktop
Classifier: Intended Audience :: Information Technology
Classifier: Intended Audience :: System Administrators
Classifier: License :: OSI Approved :: MIT License
Classifier: Operating System :: POSIX :: Linux
Classifier: Operating System :: Unix
Classifier: Programming Language :: Python
Classifier: Programming Language :: Python :: 2
Classifier: Programming Language :: Python :: 2.6
Classifier: Programming Language :: Python :: 2.7
Classifier: Programming Language :: Python :: 3
Classifier: Programming Language :: Python :: 3.4
Classifier: Programming Language :: Python :: 3.5
Classifier: Programming Language :: Python :: 3.6
Classifier: Topic :: Desktop Environment
Requires-Dist: coloredlogs (>=0.8)
Requires-Dist: executor (>=1.6)
Requires-Dist: verboselogs (>=1.0.1)
Requires-Dist: flufl.enum (>=4.0.1); python_version == "2.6" or python_version == "2.7" or python_version == "3.0" or python_version == "3.1" or python_version == "3.2" or python_version == "3.3"
